azure/mgmt/servicefabric/__init__.py
azure/mgmt/servicefabric/_configuration.py
azure/mgmt/servicefabric/_service_fabric_management_client.py
azure/mgmt/servicefabric/_version.py
azure/mgmt/servicefabric/aio/__init__.py
azure/mgmt/servicefabric/aio/_configuration.py
azure/mgmt/servicefabric/aio/_service_fabric_management_client.py
azure/mgmt/servicefabric/aio/operations/__init__.py
azure/mgmt/servicefabric/aio/operations/_application_type_versions_operations.py
azure/mgmt/servicefabric/aio/operations/_application_types_operations.py
azure/mgmt/servicefabric/aio/operations/_applications_operations.py
azure/mgmt/servicefabric/aio/operations/_cluster_versions_operations.py
azure/mgmt/servicefabric/aio/operations/_clusters_operations.py
azure/mgmt/servicefabric/aio/operations/_operations.py
azure/mgmt/servicefabric/aio/operations/_services_operations.py
azure/mgmt/servicefabric/models/__init__.py
azure/mgmt/servicefabric/models/_models.py
azure/mgmt/servicefabric/models/_models_py3.py
azure/mgmt/servicefabric/models/_service_fabric_management_client_enums.py
azure/mgmt/servicefabric/operations/__init__.py
azure/mgmt/servicefabric/operations/_application_type_versions_operations.py
azure/mgmt/servicefabric/operations/_application_types_operations.py
azure/mgmt/servicefabric/operations/_applications_operations.py
azure/mgmt/servicefabric/operations/_cluster_versions_operations.py
azure/mgmt/servicefabric/operations/_clusters_operations.py
azure/mgmt/servicefabric/operations/_operations.py
azure/mgmt/servicefabric/operations/_services_operations.py
azure_mgmt_servicefabric-2.0.0.dist-info/METADATA
azure_mgmt_servicefabric-2.0.0.dist-info/WHEEL
azure_mgmt_servicefabric-2.0.0.dist-info/top_level.txt
azure_mgmt_servicefabric-2.0.0.dist-info/RECORD
